<?xml version="1.0" encoding="utf-8"?>
<odoo>
  <data>    
    <!--  TICKET 002 ALBAGRO -  DEVELOPED BY SEBASTIAN MENDEZ  -  START   -->
    <record id="view_invoice_supplier_lst_inherit" model="ir.ui.view">
        <field name="name">account.invoice.supplier.tree.inherit</field>
        <field name="model">account.invoice</field>
        <field name="inherit_id" ref="account.invoice_supplier_tree"/>
        <field name="arch" type="xml">
            <field name="state" position="before">
                <field name="payment_date" invisible="False"/>  
            </field>
        </field>
    </record>     
    <!--  TICKET 002 ALBAGRO -  DEVELOPED BY SEBASTIAN MENDEZ  -  END   -->
  </data>
</odoo>  